saffier/__init__.py
saffier/__main__.py
saffier/exceptions.py
saffier/py.typed
saffier/testclient.py
saffier/types.py
saffier/cli/__init__.py
saffier/cli/base.py
saffier/cli/cli.py
saffier/cli/constants.py
saffier/cli/decorators.py
saffier/cli/env.py
saffier/cli/operations/__init__.py
saffier/cli/operations/branches.py
saffier/cli/operations/check.py
saffier/cli/operations/current.py
saffier/cli/operations/downgrade.py
saffier/cli/operations/edit.py
saffier/cli/operations/heads.py
saffier/cli/operations/history.py
saffier/cli/operations/init.py
saffier/cli/operations/inspectdb.py
saffier/cli/operations/list_templates.py
saffier/cli/operations/makemigrations.py
saffier/cli/operations/merge.py
saffier/cli/operations/migrate.py
saffier/cli/operations/revision.py
saffier/cli/operations/show.py
saffier/cli/operations/stamp.py
saffier/cli/operations/shell/__init__.py
saffier/cli/operations/shell/base.py
saffier/cli/operations/shell/enums.py
saffier/cli/operations/shell/ipython.py
saffier/cli/operations/shell/ptpython.py
saffier/cli/operations/shell/utils.py
saffier/cli/templates/default/README
saffier/cli/templates/default/alembic.ini.mako
saffier/cli/templates/default/env.py
saffier/cli/templates/default/script.py.mako
saffier/conf/__init__.py
saffier/conf/enums.py
saffier/conf/functional.py
saffier/conf/global_settings.py
saffier/conf/module_import.py
saffier/contrib/__init__.py
saffier/contrib/multi_tenancy/__init__.py
saffier/contrib/multi_tenancy/base.py
saffier/contrib/multi_tenancy/exceptions.py
saffier/contrib/multi_tenancy/metaclasses.py
saffier/contrib/multi_tenancy/models.py
saffier/contrib/multi_tenancy/registry.py
saffier/contrib/multi_tenancy/settings.py
saffier/contrib/multi_tenancy/utils.py
saffier/contrib/sqlalchemy/__init__.py
saffier/contrib/sqlalchemy/fields.py
saffier/contrib/sqlalchemy/protocols.py
saffier/contrib/sqlalchemy/types.py
saffier/core/__init__.py
saffier/core/datastructures.py
saffier/core/events.py
saffier/core/sync.py
saffier-1.4.2.dist-info/METADATA
saffier-1.4.2.dist-info/WHEEL
saffier-1.4.2.dist-info/entry_points.txt
saffier-1.4.2.dist-info/licenses/LICENSE
saffier-1.4.2.dist-info/RECORD
