Metadata-Version: 2.3
Name: saffier
Version: 1.4.2
Summary: The only python ORM you will ever need.
Project-URL: Homepage, https://github.com/tarsil/saffier
Project-URL: Documentation, https://saffier.tarsild.io/
Project-URL: Changelog, https://saffier.tarsild.io/release-notes/
Project-URL: Funding, https://github.com/sponsors/tarsil
Project-URL: Source, https://github.com/tarsil/saffier
Author-email: Tiago Silva <tiago.arasilva@gmail.com>
License-Expression: MIT
License-File: LICENSE
Keywords: api,asgi,fastapi,framework,http,machine learning,ml,openapi,pydantic,rest,starlette,websocket
Classifier: Development Status :: 4 - Beta
Classifier: Environment :: Web Environment
Classifier: Framework :: AnyIO
Classifier: Framework :: AsyncIO
Classifier: Intended Audience :: Developers
Classifier: Intended Audience :: Information Technology
Classifier: Intended Audience :: System Administrators
Classifier: License :: OSI Approved :: MIT License
Classifier: Operating System :: OS Independent
Classifier: Programming Language :: Python
Classifier: Programming Language :: Python :: 3
Classifier: Programming Language :: Python :: 3 :: Only
Classifier: Programming Language :: Python :: 3.8
Classifier: Programming Language :: Python :: 3.9
Classifier: Programming Language :: Python :: 3.10
Classifier: Programming Language :: Python :: 3.11
Classifier: Programming Language :: Python :: 3.12
Classifier: Topic :: Internet
Classifier: Topic :: Internet :: WWW/HTTP
Classifier: Topic :: Internet :: WWW/HTTP :: HTTP Servers
Classifier: Topic :: Software Development
Classifier: Topic :: Software Development :: Libraries
Classifier: Topic :: Software Development :: Libraries :: Application Frameworks
Classifier: Topic :: Software Development :: Libraries :: Python Modules
Classifier: Typing :: Typed
Requires-Python: >=3.8
Requires-Dist: alembic<2.0.0,>=1.11.3
Requires-Dist: anyio<5,>=4.0.0
Requires-Dist: click<9.0.0,>=8.1.3
Requires-Dist: databasez>=0.8.5
Requires-Dist: dymmond-settings>=1.0.4
Requires-Dist: loguru<0.10.0,>=0.6.0
Requires-Dist: nest-asyncio
Requires-Dist: orjson<4.0.0,>=3.8.5
Requires-Dist: pydantic<3.0.0,>=2.5.3
Requires-Dist: rich<14.0.0,>=13.3.1
Provides-Extra: all
Requires-Dist: databasez[mysql,postgresql,sqlite]; extra == 'all'
Requires-Dist: ipython<9.0.0,>=8.10.0; extra == 'all'
Requires-Dist: orjson<4.0.0,>=3.8.5; extra == 'all'
Requires-Dist: ptpython<4.0.0,>=3.0.23; extra == 'all'
Provides-Extra: dev
Requires-Dist: autoflake>=1.4.0; extra == 'dev'
Requires-Dist: flake8>=5.0.4; extra == 'dev'
Requires-Dist: pre-commit<4.0.0,>=2.17.0; extra == 'dev'
Requires-Dist: uvicorn[standard]>=0.19.0; extra == 'dev'
Requires-Dist: watchfiles<0.23.0,>=0.16.1; extra == 'dev'
Provides-Extra: doc
Requires-Dist: griffe-typingdoc>=0.2.2; extra == 'doc'
Requires-Dist: mdx-include<2.0.0,>=1.4.2; extra == 'doc'
Requires-Dist: mkautodoc<0.3.0,>=0.2.0; extra == 'doc'
Requires-Dist: mkdocs-markdownextradata-plugin<0.3.0,>=0.2.5; extra == 'doc'
Requires-Dist: mkdocs-material<10.0.0,>=9.4.4; extra == 'doc'
Requires-Dist: mkdocs-meta-descriptions-plugin>=2.3.0; extra == 'doc'
Requires-Dist: mkdocs<2.0.0,>=1.1.2; extra == 'doc'
Requires-Dist: mkdocstrings[python]<0.30.0,>=0.23.0; extra == 'doc'
Requires-Dist: pyyaml<7.0.0,>=6.0; extra == 'doc'
Provides-Extra: ipython
Requires-Dist: ipython<9.0.0,>=8.10.0; extra == 'ipython'
Provides-Extra: mysql
Requires-Dist: databasez[mysql]; extra == 'mysql'
Provides-Extra: postgres
Requires-Dist: databasez[postgresql]; extra == 'postgres'
Provides-Extra: ptpython
Requires-Dist: ptpython<4.0.0,>=3.0.23; extra == 'ptpython'
Provides-Extra: sqlite
Requires-Dist: databasez[sqlite]; extra == 'sqlite'
Provides-Extra: test
Requires-Dist: asyncmy<0.3.0,>=0.2.7; extra == 'test'
Requires-Dist: asyncpg<1,>=0.27.0; extra == 'test'
Requires-Dist: black==24.8.0; extra == 'test'
Requires-Dist: esmerald>=3.0.0; extra == 'test'
Requires-Dist: flake8>=5.0.4; extra == 'test'
Requires-Dist: freezegun<2.0.0,>=1.2.2; extra == 'test'
Requires-Dist: httpx<0.30.0,>=0.25.0; extra == 'test'
Requires-Dist: isort<6.0.0,>=5.0.6; extra == 'test'
Requires-Dist: mock==5.1.0; extra == 'test'
Requires-Dist: mypy==1.11.1; extra == 'test'
Requires-Dist: pymysql<2.0.0,>=1.0.2; extra == 'test'
Requires-Dist: pytest-asyncio>=0.19.0; extra == 'test'
Requires-Dist: pytest-cov<6.0.0,>=2.12.0; extra == 'test'
Requires-Dist: pytest<9.0.0,>=7.1.3; extra == 'test'
Requires-Dist: ruff<1.0.0,>=0.0.256; extra == 'test'
Requires-Dist: types-orjson==3.6.2; extra == 'test'
Provides-Extra: testing
Requires-Dist: sqlalchemy-utils>=0.40.0; extra == 'testing'
